<keymap version="1" name="Mac OS X copy" parent="Mac OS X">
  <action id="ActivateTerminalToolWindow">
    <keyboard-shortcut first-keystroke="alt f12" />
    <keyboard-shortcut first-keystroke="alt 5" />
  </action>
  <action id="ActivateVersionControlToolWindow">
    <keyboard-shortcut first-keystroke="shift meta 9" />
    <keyboard-shortcut first-keystroke="alt 3" />
  </action>
  <action id="CompileDirty">
    <keyboard-shortcut first-keystroke="meta f9" />
    <keyboard-shortcut first-keystroke="ctrl alt b" />
  </action>
  <action id="ReformatWithPrettierAction">
    <keyboard-shortcut first-keystroke="shift meta alt p" />
    <keyboard-shortcut first-keystroke="meta alt semicolon" />
  </action>
  <action id="RenameElement">
    <keyboard-shortcut first-keystroke="shift f6" />
    <keyboard-shortcut first-keystroke="ctrl alt r" />
  </action>
</keymap>